setup.py
mpl_render/__init__.py
mpl_render/mpl_render.py
mpl_render/version.py
mpl_render.egg-info/PKG-INFO
mpl_render.egg-info/SOURCES.txt
mpl_render.egg-info/dependency_links.txt
mpl_render.egg-info/requires.txt
mpl_render.egg-info/top_level.txt
mpl_render/example/__init__.py
mpl_render/example/mandelbrot.py
mpl_render/example/mandelbrot_ipython.py
mpl_render/example/mpl_render_example.ipynb
mpl_render/example/sin1x.py
mpl_render/trash/__init__.py
mpl_render/trash/test.py
mpl_render/trash/viewlims.py