Metadata-Version: 1.1
Name: mpl-render
Version: 0.2.3
Summary: Zoom into matplotlib 1D and 2D (imshow) plots by providing a render callback
Home-page: https://hydra.ecd.space/f/mpl_render/
Author: Eduard Christian Dumitrescu
Author-email: UNKNOWN
License: LGPLv3
Platform: UNKNOWN
Classifier: Programming Language :: Python :: 3 :: Only
